[
  {
    "description": "Login Story for Client Connect",
    "keyword": "Feature",
    "name": "Test Login",
    "line": 2,
    "id": "test-login",
    "tags": [
      {
        "name": "@BDDSTORY-TST2CP-18",
        "line": 1
      }
    ],
    "uri": "TST2CP-18.feature",
    "elements": [
      {
        "id": "test-login;test-login-with-invalid-credentials",
        "keyword": "Scenario",
        "line": 7,
        "name": "Test Login With Invalid Credentials",
        "tags": [
          {
            "name": "@BDDSTORY-TST2CP-18",
            "line": 1
          },
          {
            "name": "@BDDTEST-TST2CP-20",
            "line": 6
          }
        ],
        "type": "scenario",
        "steps": [
          {
            "arguments": [],
            "keyword": "Given ",
            "line": 9,
            "name": "I open home page",
            "result": {
              "status": "passed",
              "duration": 2051000000
            }
          },
          {
            "arguments": [],
            "keyword": "When ",
            "line": 10,
            "name": "Click Login link",
            "result": {
              "status": "passed",
              "duration": 1185000000
            }
          },
          {
            "arguments": [],
            "keyword": "Then ",
            "line": 11,
            "name": "I see UserName Field",
            "result": {
              "status": "passed",
              "duration": 20000000
            }
          }
        ]
      },
      {
        "id": "test-login;test-login-with-valid-credentials",
        "keyword": "Scenario",
        "line": 14,
        "name": "Test Login With Valid Credentials",
        "tags": [
          {
            "name": "@BDDSTORY-TST2CP-18",
            "line": 1
          },
          {
            "name": "@BDDTEST-TST2CP-19",
            "line": 13
          }
        ],
        "type": "scenario",
        "steps": [
          {
            "arguments": [],
            "keyword": "Given ",
            "line": 16,
            "name": "I open home page",
            "result": {
              "status": "passed",
              "duration": 1351000000
            }
          },
          {
            "arguments": [],
            "keyword": "When ",
            "line": 17,
            "name": "Click Login link",
            "result": {
              "status": "passed",
              "duration": 1043000000
            }
          },
          {
            "arguments": [],
            "keyword": "Then ",
            "line": 18,
            "name": "I see UserName Field",
            "result": {
              "status": "passed",
              "duration": 11000000
            }
          }
        ]
      }
    ]
  }
]